ice_simplex_assimilate/__init__.py
ice_simplex_assimilate-0.1.17.dist-info/METADATA
ice_simplex_assimilate-0.1.17.dist-info/WHEEL
ice_simplex_assimilate-0.1.17.dist-info/RECORD
